cachecontrol_sqlite/__init__.py
cachecontrol_sqlite-0.1.0.dist-info/DESCRIPTION.rst
cachecontrol_sqlite-0.1.0.dist-info/METADATA
cachecontrol_sqlite-0.1.0.dist-info/RECORD
cachecontrol_sqlite-0.1.0.dist-info/WHEEL
cachecontrol_sqlite-0.1.0.dist-info/metadata.json
cachecontrol_sqlite-0.1.0.dist-info/top_level.txt
