Metadata-Version: 2.0
Name: cachecontrol-sqlite
Version: 0.1.0
Summary: SQLite backend for requests CacheControl
Home-page: https://github.com/ishitatsuyuki/cachecontrol-sqlite
Author: Tatsuyuki Ishi
Author-email: ishitatsuyuki@protonmail.com
License: Apache-2.0
Platform: UNKNOWN
Classifier: Development Status :: 4 - Beta
Classifier: Intended Audience :: Developers
Classifier: Topic :: Software Development :: Libraries :: Python Modules
Classifier: License :: OSI Approved :: Apache Software License
Classifier: Programming Language :: Python :: 2
Classifier: Programming Language :: Python :: 2.7
Classifier: Programming Language :: Python :: 3
Classifier: Programming Language :: Python :: 3.6
Requires-Dist: CacheControl
